ansible_hostmanager/__init__.py
ansible_hostmanager-0.2.5.dist-info/METADATA
ansible_hostmanager-0.2.5.dist-info/RECORD
ansible_hostmanager-0.2.5.dist-info/WHEEL
ansible_hostmanager-0.2.5.dist-info/entry_points.txt
ansible_hostmanager-0.2.5.dist-info/top_level.txt
