Metadata-Version: 2.1
Name: ansible-hostmanager
Version: 0.2.5
Summary: CLI script to work with Ansible hosts file
Home-page: https://github.com/maxzheng/ansible-hostmanager
Author: Max Zheng
Author-email: maxzheng.os@gmail.com
License: MIT
Keywords: list ssh Ansible hosts file
Platform: UNKNOWN
Classifier: Development Status :: 5 - Production/Stable
Classifier: Intended Audience :: Developers
Classifier: Topic :: Software Development :: User Interfaces
Classifier: License :: OSI Approved :: MIT License
Classifier: Programming Language :: Python :: 3
Classifier: Programming Language :: Python :: 3.6
Requires-Python: >=3.6
Requires-Dist: ansible
Requires-Dist: click
Requires-Dist: localconfig (>=1.1)
Requires-Dist: tabulate
Requires-Dist: utils-core
